dbr/__init__.py
dbr/core.py
ceshiCreate-1.0.4.dist-info/LICENSE.txt
ceshiCreate-1.0.4.dist-info/METADATA
ceshiCreate-1.0.4.dist-info/WHEEL
ceshiCreate-1.0.4.dist-info/top_level.txt
ceshiCreate-1.0.4.dist-info/RECORD
