Metadata-Version: 2.1
Name: ceshiCreate
Version: 1.0.4
Summary: Dynamsoft Barcode Reader Python project
Home-page: https://mail.163.com/js6/main.jsp?sid=PAlGWIYldfIQjfQTFYllFVEyKXidwtNk&df=mail163_letter#module=welcome.WelcomeModule%7C%7B%7D
Author: wangweidong
Author-email: 17891967090@163.com
License: Apache
Classifier: License :: OSI Approved :: Apache Software License
Classifier: Natural Language :: English
Classifier: Operating System :: OS Independent
Classifier: Programming Language :: Python
Classifier: Programming Language :: Python :: 3.6
Classifier: Topic :: Software Development :: Libraries :: Python Modules
Requires-Python: >=3.8
License-File: LICENSE.txt
Requires-Dist: requests (>=2.0.0)
